editorconfig_checker/__init__.py
editorconfig_checker/__main__.py
editorconfig_checker/wrapper.py
editorconfig_checker/lib/ec-darwin-386.tar.gz
editorconfig_checker/lib/ec-darwin-amd64.tar.gz
editorconfig_checker/lib/ec-dragonfly-amd64.tar.gz
editorconfig_checker/lib/ec-freebsd-386.tar.gz
editorconfig_checker/lib/ec-freebsd-amd64.tar.gz
editorconfig_checker/lib/ec-freebsd-arm.tar.gz
editorconfig_checker/lib/ec-linux-386.tar.gz
editorconfig_checker/lib/ec-linux-amd64.tar.gz
editorconfig_checker/lib/ec-linux-arm.tar.gz
editorconfig_checker/lib/ec-linux-arm64.tar.gz
editorconfig_checker/lib/ec-linux-mips.tar.gz
editorconfig_checker/lib/ec-linux-mips64.tar.gz
editorconfig_checker/lib/ec-linux-mips64le.tar.gz
editorconfig_checker/lib/ec-linux-mipsle.tar.gz
editorconfig_checker/lib/ec-linux-ppc64.tar.gz
editorconfig_checker/lib/ec-linux-ppc64le.tar.gz
editorconfig_checker/lib/ec-netbsd-386.tar.gz
editorconfig_checker/lib/ec-netbsd-amd64.tar.gz
editorconfig_checker/lib/ec-netbsd-arm.tar.gz
editorconfig_checker/lib/ec-openbsd-386.tar.gz
editorconfig_checker/lib/ec-openbsd-amd64.tar.gz
editorconfig_checker/lib/ec-openbsd-arm.tar.gz
editorconfig_checker/lib/ec-plan9-386.tar.gz
editorconfig_checker/lib/ec-plan9-amd64.tar.gz
editorconfig_checker/lib/ec-solaris-amd64.tar.gz
editorconfig_checker/lib/ec-windows-386.exe.tar.gz
editorconfig_checker/lib/ec-windows-amd64.exe.tar.gz
editorconfig_checker-2.3.51.dist-info/LICENSE
editorconfig_checker-2.3.51.dist-info/METADATA
editorconfig_checker-2.3.51.dist-info/WHEEL
editorconfig_checker-2.3.51.dist-info/entry_points.txt
editorconfig_checker-2.3.51.dist-info/top_level.txt
editorconfig_checker-2.3.51.dist-info/RECORD
